qweather_mcp/__init__.py
qweather_mcp/__main__.py
qweather_mcp/config.py
qweather_mcp/main.py
qweather_mcp-0.2.12.dist-info/METADATA
qweather_mcp-0.2.12.dist-info/WHEEL
qweather_mcp-0.2.12.dist-info/entry_points.txt
qweather_mcp-0.2.12.dist-info/licenses/LICENSE
qweather_mcp-0.2.12.dist-info/RECORD
