Metadata-Version: 2.4
Name: qweather-mcp
Version: 0.2.12
Summary: 和风天气查询API服务，支持MCP接口可被AI助手直接调用
Project-URL: Homepage, https://gitcode.com/huqi/weather-mcp
Project-URL: Bug Tracker, https://gitcode.com/huqi/weather-mcp/issues
Project-URL: Documentation, https://gitcode.com/huqi/weather-mcp/blob/main/README.md
Author-email: "zishu.co" <huqi1024@gmail.com>
License: MIT License
License-File: LICENSE
Keywords: ai,api,fastapi,mcp,weather
Classifier: Development Status :: 4 - Beta
Classifier: License :: OSI Approved :: MIT License
Classifier: Operating System :: OS Independent
Classifier: Programming Language :: Python :: 3
Classifier: Programming Language :: Python :: 3.8
Classifier: Programming Language :: Python :: 3.9
Classifier: Programming Language :: Python :: 3.10
Classifier: Programming Language :: Python :: 3.11
Classifier: Topic :: Internet :: WWW/HTTP :: HTTP Servers
Classifier: Topic :: Software Development :: Libraries :: Python Modules
Requires-Python: >=3.10
Requires-Dist: cryptography>=40.0.0
Requires-Dist: fastapi-mcp>=0.3.4
Requires-Dist: fastapi>=0.95.0
Requires-Dist: pydantic>=2.0.0
Requires-Dist: pyjwt>=2.6.0
Requires-Dist: python-dotenv>=1.0.0
Requires-Dist: requests>=2.28.0
Requires-Dist: uvicorn>=0.22.0
